lab2/homework7/submodule_dff.v
module submodule_dff (Q, D, Clock);
	output reg Q; 
    input Clock;
	input D;
    initial Q<=0;
always @ (posedge Clock)
	begin
		Q <= D;
	end
endmodule

lab2/homework7/submodule_xor.v
module submodule_xor(
    output wire XOR,
    input wire A,B
);
xor U0 (XOR, A, B);
endmodule

lab2/homework7/toplevel_hw_7.v
`include "submodule_dff.v"
`include "submodule_xor.v"
module toplevel_hw_7(
    output wire out,
    input wire in,Clock
);
wire XOR;
submodule_xor U0 (XOR,in,out); // XOR is data in to D Flip Flop
submodule_dff U1 (out,XOR,Clock);
endmodule

lab2/homework7/homework7_tb.v
//`timescale 1ns / 1ps
`include "toplevel_hw_7.v"

module homework7_tb;
    reg in;
    reg Clock;
    wire out;   

    toplevel_hw_7 DUT(.in(in),.Clock(Clock),
        .out(out));
    integer i;
    initial begin
        $dumpfile("homework7_tb.vcd");
        $dumpvars;
        in=1;
        Clock=0;
        // forever #10 CLK = ~CLK;
        //          OR
	    for (i=0; i <=10; i=i+1)
	    #10 Clock = ~Clock; 
    end 
    initial begin 
			 in <= 0;
         #8; in <= 0;
        #10; in <= 0;
        #10; in <= 1;
        #10; in <= 1;
        #10; in <= 1;
        #10; in <= 1;
        #10;
    end 
	initial begin
	    $monitor("Clock=%d,D=%d,out=%d \n",Clock,in,out);
	end    
endmodule

lab2/homework7/homework7_tb.vcd
$date
	Sun Jan 10 23:22:45 2021
$end
$version
	Icarus Verilog
$end
$timescale
	1s
$end
$scope module homework7_tb $end
$var wire 1 ! out $end
$var reg 1 " Clock $end
$var reg 1 # in $end
$var integer 32 $ i [31:0] $end
$scope module DUT $end
$var wire 1 " Clock $end
$var wire 1 # in $end
$var wire 1 ! out $end
$var wire 1 % XOR $end
$scope module U0 $end
$var wire 1 # A $end
$var wire 1 % XOR $end
$var wire 1 ! B $end
$upscope $end
$scope module U1 $end
$var wire 1 " Clock $end
$var wire 1 % D $end
$var reg 1 ! Q $end
$upscope $end
$upscope $end
$upscope $end
$enddefinitions $end
#0
$dumpvars
1%
b0 $
1#
0"
0!
$end
#10
0%
1!
b1 $
1"
#20
b10 $
0"
#30
1%
0!
b11 $
1"
#40
b100 $
0"
#50
0%
1!
b101 $
1"
#60
b110 $
0"
#70
1%
0!
b111 $
1"
#80
b1000 $
0"
#90
0%
1!
b1001 $
1"
#100
b1010 $
0"
#110
1%
0!
b1011 $
1"
