lab2/homework1/dff.v
`timescale 1ns / 1ps
// Verilog code for D Flip FLop
module dff (CLK, D, Q);
	input CLK;
	input D;
	output reg Q; 

// The posedge keyword specifies the direction 
// of the clock signal changing from 0 to 1. 
always @ (posedge CLK)
	begin
		Q <= D;
	end

endmodule

lab2/homework1/dff_tb.v
//testbench for DFF
`timescale 1ns / 1ps
module dff_tb;
    reg CLK;
    reg D;
    wire Q;
    dff DUT(
        .CLK(CLK),
        .D(D),
		.Q(Q));
    integer i;
    initial begin
        $dumpfile("dff_tb.vcd");
        $dumpvars;        
        D=0;
        CLK=0;
        // forever #10 CLK = ~CLK;
        //          OR
	    for (i=0; i <=10; i=i+1)
	    #10 CLK = ~CLK; 
    end 
    initial begin 
			 D <= 0;
         #8; D <= 1;
        #10; D <= 0;
        #10; D <= 0;
        #10; D <= 1;
        #10; D <= 0;
        #10; D <= 1;
        #10;
    end 
	initial begin
	    $monitor("Clock=%d,D=%d,Q=%d \n",CLK,D,Q);
	end    
endmodule

lab2/homework1/dff_tb.vcd
$date
	Sat Jan  9 23:39:04 2021
$end
$version
	Icarus Verilog
$end
$timescale
	1ps
$end
$scope module dff_tb $end
$var wire 1 ! Q $end
$var reg 1 " CLK $end
$var reg 1 # D $end
$var integer 32 $ i [31:0] $end
$scope module DUT $end
$var wire 1 " CLK $end
$var wire 1 # D $end
$var reg 1 ! Q $end
$upscope $end
$upscope $end
$enddefinitions $end
#0
$dumpvars
b0 $
0#
0"
x!
$end
#8000
1#
#10000
1!
b1 $
1"
#18000
0#
#20000
b10 $
0"
#30000
0!
b11 $
1"
#38000
1#
#40000
b100 $
0"
#48000
0#
#50000
b101 $
1"
#58000
1#
#60000
b110 $
0"
#70000
1!
b111 $
1"
#80000
b1000 $
0"
#90000
b1001 $
1"
#100000
b1010 $
0"
#110000
b1011 $
1"
