lab2/homework3/dff8.v
`timescale 1ns / 1ps
// * positive-edge triggered
// * synchronous active-high/low reset
module dff8 (
	output reg [7:0] q,
    input reset, 
    input clock,
	input [7:0] d
);

always @ (posedge clock)
	begin
        if(!reset) 
            q <= 8'b00000000; 
        else    
            q <= d;
    end    
endmodule

lab2/homework3/dff8_tb.v
`timescale 1ns / 1ps
module dff8_tb;
    reg [7:0] d;
    reg clock;
    reg reset;
    wire [7:0] q;
    
    dff8 DUT(.d(d),.clock(clock),.reset(reset),
		.q(q));
    integer i;
    initial begin
        $dumpfile("dff8_tb.vcd");
        $dumpvars;
        clock=1'b0;
        reset=0;
        // forever #10 CLK = ~CLK;
        //          OR
	    for (i=0; i <=10; i=i+1)
	    #10 clock = ~clock;  
    end 
    
    initial begin 
             reset=0;
			       d <= 8'bxxxxxxxx;
         #8; d <= 8'b11110011;
        #10; reset=1;
             d <= 8'b10000011;
        #10; 
    end 
    initial begin
	    $monitor("Clock=%d,d=%d,q=%d \n",clock,d,q);
	end  
endmodule

lab2/homework3/dff8_tb.vcd
$date
	Tue Jan 12 20:55:31 2021
$end
$version
	Icarus Verilog
$end
$timescale
	1ps
$end
$scope module dff8_tb $end
$var wire 8 ! q [7:0] $end
$var reg 1 " clock $end
$var reg 8 # d [7:0] $end
$var reg 1 $ reset $end
$var integer 32 % i [31:0] $end
$scope module DUT $end
$var wire 1 " clock $end
$var wire 8 & d [7:0] $end
$var wire 1 $ reset $end
$var reg 8 ' q [7:0] $end
$upscope $end
$upscope $end
$enddefinitions $end
#0
$dumpvars
bx '
bx &
b0 %
0$
bx #
0"
bx !
$end
#8000
b11110011 #
b11110011 &
#10000
b0 !
b0 '
b1 %
1"
#18000
b10000011 #
b10000011 &
1$
#20000
b10 %
0"
#30000
b10000011 !
b10000011 '
b11 %
1"
#40000
b100 %
0"
#50000
b101 %
1"
#60000
b110 %
0"
#70000
b111 %
1"
#80000
b1000 %
0"
#90000
b1001 %
1"
#100000
b1010 %
0"
#110000
b1011 %
1"
