lab1/homework3/homework3.v
// Code your design here
`timescale 1ns / 1ps

module homework3(
    input [1:0]x,
    input [1:0]y,
    output z
);
assign z=   ((x==2'b00) && (y==2'b00)) ? 1'b1 :
            ((x==2'b10) && (y==2'b10)) ? 1'b1 :
            ((x==2'b01) && (y==2'b01)) ? 1'b1 :
            ((x==2'b11) && (y==2'b11)) ? 1'b1 :
            2'b0;
endmodule

lab1/homework3/homework3_tb.v
//testbench for homework3
`timescale 1ns / 1ps

module homework3_tb;
    reg [1:0] x, y;
    wire z;

    homework3 DUT(
        .x(x),
        .y(y),
        .z(z)
    );

    initial begin
        $dumpfile("homework3_tb.vcd");
        $dumpvars;
             x=2'b00; y=2'b00;
        #0.1 x=2'b00; y=2'b01;
        #0.1 x=2'b00; y=2'b10;
        #0.1 x=2'b00; y=2'b11;
        #0.1 x=2'b01; y=2'b00;
        #0.1 x=2'b01; y=2'b01;
        #0.1 x=2'b01; y=2'b10;
        #0.1 x=2'b01; y=2'b11;
        #0.1 x=2'b10; y=2'b00;
        #0.1 x=2'b10; y=2'b01;
        #0.1 x=2'b10; y=2'b10;
        #0.1 x=2'b10; y=2'b11;
        #0.1 x=2'b11; y=2'b00;
        #0.1 x=2'b11; y=2'b01;
        #0.1 x=2'b11; y=2'b10;
        #0.1 x=2'b11; y=2'b11;
        #0.1;
    end
    
    initial begin
        $monitor("x=%d,y=%d,z=%d \n",x,y,z);
    end
endmodule

lab1/homework3/homework3_tb.vcd
$date
	Sun Nov 29 14:28:13 2020
$end
$version
	Icarus Verilog
$end
$timescale
	1ps
$end
$scope module homework3_tb $end
$var wire 1 ! z $end
$var reg 2 " x [1:0] $end
$var reg 2 # y [1:0] $end
$scope module DUT $end
$var wire 2 $ x [1:0] $end
$var wire 2 % y [1:0] $end
$var wire 1 ! z $end
$upscope $end
$upscope $end
$enddefinitions $end
#0
$dumpvars
b0 %
b0 $
b0 #
b0 "
1!
$end
#100
0!
b1 #
b1 %
#200
b10 #
b10 %
#300
b11 #
b11 %
#400
b0 #
b0 %
b1 "
b1 $
#500
1!
b1 #
b1 %
#600
0!
b10 #
b10 %
#700
b11 #
b11 %
#800
b0 #
b0 %
b10 "
b10 $
#900
b1 #
b1 %
#1000
1!
b10 #
b10 %
#1100
0!
b11 #
b11 %
#1200
b0 #
b0 %
b11 "
b11 $
#1300
b1 #
b1 %
#1400
b10 #
b10 %
#1500
1!
b11 #
b11 %
