lab1/homework8/c/submodule_hw_8_c_xor.v
module submodule_hw_8_c_xor(
    output wire F1,
    input wire A,B
);
xor U0 (F1, A, B);
endmodule

lab1/homework8/c/submodule_hw_8_c_or.v
module submodule_hw_8_c_or(
    output wire F1,
    input wire A,B
);
or U0 (F1, A, B);
endmodule

lab1/homework8/c/submodule_hw_8_c_not.v
module submodule_hw_8_c_not(
    output wire F1,
    input wire A
);
not U0 (F1, A);
endmodule

lab1/homework8/c/toplevel_hw_8_c.v
`include "submodule_hw_8_c_or.v"
`include "submodule_hw_8_c_not.v"
`include "submodule_hw_8_c_xor.v"

module toplevel_hw_8_c(
    output wire F,
    input wire X,Y,Z
);

wire OR1,NOTX,OR2,XOR1;
submodule_hw_8_c_or U0 (OR1,X,Y);
submodule_hw_8_c_not U1 (NOTX,X);
submodule_hw_8_c_xor U2 (XOR1,Y,Z);
submodule_hw_8_c_or U3 (OR2,NOTX,XOR1);
submodule_hw_8_c_xor U4 (F,XOR1,OR2);
endmodule

lab1/homework8/c/homework8_c_tb.v
//testbench for homework1
`timescale 1ns / 1ps
`include "toplevel_hw_8_c.v"

module homework8_c_tb;
    reg X;
    reg Y;
    reg Z;
    wire F;

    toplevel_hw_8_c DUT(
        .X(X),
        .Y(Y),
        .Z(Z),
        .F(F)
    );

    initial begin
        $dumpfile("homework8_c_tb.vcd");
        $dumpvars;
             X=1'b0; Y=1'b0; Z=1'b0;
        #10 X=1'b0; Y=1'b0; Z=1'b1;
        #10 X=1'b0; Y=1'b1; Z=1'b0;
        #10 X=1'b0; Y=1'b1; Z=1'b1;
        #10 X=1'b1; Y=1'b0; Z=1'b0;
        #10 X=1'b1; Y=1'b0; Z=1'b1;
        #10 X=1'b1; Y=1'b1; Z=1'b0;
        #10 X=1'b1; Y=1'b1; Z=1'b1;
        #10;
    end
    
    initial begin
        $monitor("X=%d,Y=%d,Z=%d,F=%d \n",X,Y,Z,F);
    end
endmodule

lab1/homework8/c/homework8_c_tb.vcd
$date
	Tue Dec  1 16:21:34 2020
$end
$version
	Icarus Verilog
$end
$timescale
	1ps
$end
$scope module homework8_c_tb $end
$var wire 1 ! F $end
$var reg 1 " X $end
$var reg 1 # Y $end
$var reg 1 $ Z $end
$scope module DUT $end
$var wire 1 " X $end
$var wire 1 # Y $end
$var wire 1 $ Z $end
$var wire 1 % XOR1 $end
$var wire 1 & OR2 $end
$var wire 1 ' OR1 $end
$var wire 1 ( NOTX $end
$var wire 1 ! F $end
$scope module U0 $end
$var wire 1 " A $end
$var wire 1 # B $end
$var wire 1 ' F1 $end
$upscope $end
$scope module U1 $end
$var wire 1 " A $end
$var wire 1 ( F1 $end
$upscope $end
$scope module U2 $end
$var wire 1 # A $end
$var wire 1 $ B $end
$var wire 1 % F1 $end
$upscope $end
$scope module U3 $end
$var wire 1 ( A $end
$var wire 1 % B $end
$var wire 1 & F1 $end
$upscope $end
$scope module U4 $end
$var wire 1 % A $end
$var wire 1 & B $end
$var wire 1 ! F1 $end
$upscope $end
$upscope $end
$upscope $end
$enddefinitions $end
#0
$dumpvars
1(
0'
1&
0%
0$
0#
0"
1!
$end
#10000
0!
1%
1$
#20000
1'
0$
1#
#30000
1!
0%
1$
#40000
0!
0&
0(
0$
0#
1"
#50000
1&
0!
1%
1$
#60000
0$
1#
#70000
0&
0!
0%
1$
