lab2/homework6/dff16_SyncReset.v
`timescale 1ns / 1ps

module dff16_SyncReset (clock, CE, d, q, reset);
	input clock;
	input CE;
	input [15:0] d;
	input reset;
	output reg [15:0] q; 


always @ (posedge clock)
	begin
		
		if(!reset) 
			q <= 16'b0000000000000000; 
		else
			if ( CE == 1)
				q <= d;	
	end

endmodule

lab2/homework6/dff16_SyncReset_tb.v
`timescale 1ns / 1ps
module dff16_SyncReset_tb;
    reg [15:0] d;
    reg clock;
    reg reset;
    reg CE;
    wire [15:0] q;
    
    dff16_SyncReset DUT(.d(d),.clock(clock),.reset(reset),.CE(CE),
		.q(q));
    integer i;
    initial begin
        $dumpfile("dff16_SyncReset_tb.vcd");
        $dumpvars;
        clock=1'b0;
        reset=0;
        // forever #10 CLK = ~CLK;
        //          OR
	    for (i=0; i <=10; i=i+1)
	    #10 clock = ~clock;  
    end 
    
    initial begin 
             reset=0;
			 CE=1'b0;
             d <= 16'bxxxxxxxxxxxxxxxx;
         #8; d <= 16'b1110111110010011;
        #10; reset=1;
             CE=1'b1;
             d <= 16'b1000001000000001;
        #10; 
    end 
    initial begin
	    $monitor("Clock=%d,d=%d,q=%d \n",clock,d,q);
	end  
endmodule

lab2/homework6/dff16_SyncReset_tb.vcd
$date
	Tue Jan 12 23:23:17 2021
$end
$version
	Icarus Verilog
$end
$timescale
	1ps
$end
$scope module dff16_SyncReset_tb $end
$var wire 16 ! q [15:0] $end
$var reg 1 " CE $end
$var reg 1 # clock $end
$var reg 16 $ d [15:0] $end
$var reg 1 % reset $end
$var integer 32 & i [31:0] $end
$scope module DUT $end
$var wire 1 " CE $end
$var wire 1 # clock $end
$var wire 16 ' d [15:0] $end
$var wire 1 % reset $end
$var reg 16 ( q [15:0] $end
$upscope $end
$upscope $end
$enddefinitions $end
#0
$dumpvars
bx (
bx '
b0 &
0%
bx $
0#
0"
bx !
$end
#8000
b1110111110010011 $
b1110111110010011 '
#10000
b0 !
b0 (
b1 &
1#
#18000
b1000001000000001 $
b1000001000000001 '
1"
1%
#20000
b10 &
0#
#30000
b1000001000000001 !
b1000001000000001 (
b11 &
1#
#40000
b100 &
0#
#50000
b101 &
1#
#60000
b110 &
0#
#70000
b111 &
1#
#80000
b1000 &
0#
#90000
b1001 &
1#
#100000
b1010 &
0#
#110000
b1011 &
1#
