lab3/homework3/fsm.v
`timescale 1ns/1ps
module ask3 (output reg out, input wire clk, reset, in);
    reg [1:0]state;
    parameter A=2'b00, B=2'b01, C=2'b10, D=2'b11;
    always @(posedge clk or negedge reset)
        if(reset==1'b0)
            begin
            state=A;
            out=0;
            end
        else
            begin
            case (state)
            A:
                begin
                    out=0;
                    if(in==1) state=B;
                    else state=A;
                end
            B:
                begin
                    out=0;
                    if(in==0) state=C;
                    else state=B;
                end
            C:
                begin
                    out=1;
                    if(in==1) state=D;
                    else state=A;
                end
            D:
                begin
                    out=1;
                    if(in==0) state=C;
                    else state=B;
                end
            default: state=A;
            endcase
        end
endmodule

lab3/homework3/fsm_tb.v
`timescale 1ns/1ps

module ask3_tb;

    reg clk, reset, in;
    wire out;

    ask3 DUT( .out(out), .clk(clk), .reset(reset), .in(in));

    initial begin
    $dumpfile("ask3_tb.vcd");
    $dumpvars;

    clk=0;
    reset=0;
    in=0;

    #0.1 reset=1;
    #0.1 clk=1; in=0;
    #0.1 clk=0;
    #0.1 clk=1; in=1; 
    #0.1 clk=0;
    #0.1 clk=1; 
    #0.1 clk=0;
    #0.1 clk=1; in=0;
    #0.1 clk=0;
    #0.1 clk=1; in=1; 
    #0.1 clk=0;
    #0.1 clk=1; in=1; 
    #0.1 clk=0;
    #0.1 clk=1; in=0; 
    #0.1 clk=0;
    #0.1 clk=1;  
    #0.1 clk=0;
    #0.1 clk=1; in=1; 
    #0.1 clk=0;
    #0.1 clk=1;
    #0.1 clk=0;

    end
endmodule

lab3/homework3/ask3_tb.vcd
$date
	Sat Jan 16 22:53:29 2021
$end
$version
	Icarus Verilog
$end
$timescale
	1ps
$end
$scope module ask3_tb $end
$var wire 1 ! out $end
$var reg 1 " clk $end
$var reg 1 # in $end
$var reg 1 $ reset $end
$scope module DUT $end
$var wire 1 " clk $end
$var wire 1 # in $end
$var wire 1 $ reset $end
$var reg 1 ! out $end
$var reg 2 % state [1:0] $end
$upscope $end
$upscope $end
$enddefinitions $end
#0
$dumpvars
b0 %
0$
0#
0"
0!
$end
#100
1$
#200
1"
#300
0"
#400
b1 %
1#
1"
#500
0"
#600
1"
#700
0"
#800
b10 %
0#
1"
#900
0"
#1000
b11 %
1!
1#
1"
#1100
0"
#1200
b1 %
1"
#1300
0"
#1400
b10 %
0!
0#
1"
#1500
0"
#1600
b0 %
1!
1"
#1700
0"
#1800
b1 %
0!
1#
1"
